drf_schemas/__init__.py
drf_schemas/admin.py
drf_schemas/apps.py
drf_schemas/models.py
drf_schemas/resources.py
drf_schemas/serializers.py
drf_schemas/services.py
drf_schemas/settings.py
drf_schemas/signals.py
drf_schemas/urls.py
drf_schemas/migrations/0001_initial.py
drf_schemas/migrations/0002_auto_20200422_1811.py
drf_schemas/migrations/0003_remove_itemfield_create_target.py
drf_schemas/migrations/__init__.py
drf_schemas/views/__init__.py
drf_schemas/views/_mixins.py
drf_schemas/views/exports.py
drf_schemas/views/fields.py
drf_schemas/views/items.py
drf_schemas/views/values.py
drf_schemas-0.1.10.dist-info/LICENSE
drf_schemas-0.1.10.dist-info/METADATA
drf_schemas-0.1.10.dist-info/WHEEL
drf_schemas-0.1.10.dist-info/top_level.txt
drf_schemas-0.1.10.dist-info/RECORD
