Metadata-Version: 2.1
Name: drf-schemas
Version: 0.1.10
Summary: Dynamic schema builder api with Django REST Framework.
Home-page: https://github.com/altest-com/drf-schemas
Author: Raikel Bordón López
Author-email: raikelbl@gmail.com
License: MIT
Platform: UNKNOWN
Classifier: Development Status :: 1 - Planning
Classifier: Environment :: Web Environment
Classifier: Framework :: Django
Classifier: Framework :: Django :: 2.2
Classifier: Framework :: Django :: 3.0
Classifier: Intended Audience :: Developers
Classifier: License :: OSI Approved :: MIT License
Classifier: Operating System :: OS Independent
Classifier: Natural Language :: English
Classifier: Programming Language :: Python :: 3
Classifier: Programming Language :: Python :: 3.5
Classifier: Programming Language :: Python :: 3.6
Classifier: Programming Language :: Python :: 3.7
Classifier: Programming Language :: Python :: 3.8
Classifier: Topic :: Internet :: WWW/HTTP
Classifier: Topic :: Internet :: WWW/HTTP :: Dynamic Content
Classifier: Topic :: Software Development :: Libraries :: Python Modules
Requires-Python: >=3.6.0
Requires-Dist: Django (>=2.2.4)
Requires-Dist: djangorestframework (>=3.10.2)
Requires-Dist: Pillow (>=6.1.0)
Requires-Dist: tablib (>=1.1.0)
Requires-Dist: django-import-export (>=2.0.2)
